[{"codigo": "IFD1020CHAIR-T", "coleccion": "TERRA BROWN"}, {"codigo": "IFD1091CHUBN", "coleccion": "CAFÉ ARUBA"}, {"codigo": "IFD1161CNS", "coleccion": "OREGON RANCH"}, {"codigo": "IFD1171CNF", "coleccion": "NATURAL TECA"}, {"codigo": "IFD1181BKS", "coleccion": "MOKA"}, {"codigo": "IFD1181BKSGN", "coleccion": "MOKA VERDE"}, {"codigo": "IFD1181CNS", "coleccion": "MOKA / DARK MOKA"}, {"codigo": "IFD1200CHEST", "coleccion": "MADEIRA"}, {"codigo": "IFD1200DSR", "coleccion": "MADEIRA"}, {"codigo": "IFD1200FTBD-EK", "coleccion": "MADEIRA"}, {"codigo": "IFD1200FTBD-Q", "coleccion": "MADEIRA"}, {"codigo": "IFD1200HDBD-EK", "coleccion": "MADEIRA"}, {"codigo": "IFD1200HDBD-Q", "coleccion": "MADEIRA"}, {"codigo": "IFD1200MIRR", "coleccion": "MADEIRA"}, {"codigo": "IFD1200NTST", "coleccion": "MADEIRA"}, {"codigo": "IFD1200RAILS-EK", "coleccion": "MADEIRA"}, {"codigo": "IFD1200RAILS-Q", "coleccion": "MADEIRA"}, {"codigo": "IFD1261CNS", "coleccion": "NEGRO MATE"}, {"codigo": "IFD1281BKS", "coleccion": "MOKA WHITE"}, {"codigo": "IFD1281CNS", "coleccion": "MOKA WHITE / MOKA CAFÉ"}, {"codigo": "IFD2221CNS", "coleccion": "SAN LUIS CUERPO / MEZQUITE ACCESORIO"}, {"codigo": "IFD2221DSK", "coleccion": "SAN LUIS CUERPO / MEZQUITE ACCESORIO"}, {"codigo": "IFD2411CKT", "coleccion": "GRIS MITA / PAJA MITA"}, {"codigo": "IFD2411CST", "coleccion": "GRIS MITA / PAJA MITA"}, {"codigo": "IFD2411END", "coleccion": "GRIS MITA / PAJA MITA"}, {"codigo": "IFD2411SOF", "coleccion": "GRIS MITA / PAJA MITA"}, {"codigo": "IFD2471CNSBL", "coleccion": "ARCADIA BLUE-WHITE BALAM"}, {"codigo": "IFD2471CNSDK", "coleccion": "ARCADIA DARK BLUE-ARCADIA CAFÉ"}, {"codigo": "IFD2471CNSOL", "coleccion": "ARCADIA VERDE-ARCADIA CAFÉ"}, {"codigo": "IFD2822CHU", "coleccion": "ARUBA NATURAL"}, {"codigo": "IFD2953CHUBG", "coleccion": "CAFÉ SAHARA"}, {"codigo": "IFD3211CKT", "coleccion": "ONIX"}, {"codigo": "IFD3211CST", "coleccion": "ONIX"}, {"codigo": "IFD3211END", "coleccion": "ONIX"}, {"codigo": "IFD3211SFT", "coleccion": "ONIX"}, {"codigo": "IFD3421CHR", "coleccion": "WALNUT"}, {"codigo": "IFD3421CHT", "coleccion": "WALNUT"}, {"codigo": "IFD3421CHU", "coleccion": "WALNUT"}, {"codigo": "IFD3421CKT", "coleccion": "WALNUT"}, {"codigo": "IFD3421CNS", "coleccion": "WALNUT"}, {"codigo": "IFD3421CST", "coleccion": "WALNUT"}, {"codigo": "IFD3421DSR", "coleccion": "WALNUT"}, {"codigo": "IFD3421END", "coleccion": "WALNUT"}, {"codigo": "IFD3421FTBEK", "coleccion": "WALNUT"}, {"codigo": "IFD3421FTBQE", "coleccion": "WALNUT"}, {"codigo": "IFD3421HBDEK", "coleccion": "WALNUT"}, {"codigo": "IFD3421HBDQE", "coleccion": "WALNUT"}, {"codigo": "IFD3421MIR", "coleccion": "WALNUT"}, {"codigo": "IFD3421NTS", "coleccion": "WALNUT"}, {"codigo": "IFD3421RLSCK", "coleccion": "WALNUT"}, {"codigo": "IFD3421RLSEK", "coleccion": "WALNUT"}, {"codigo": "IFD3421RLSQE", "coleccion": "WALNUT"}, {"codigo": "IFD3421SFT", "coleccion": "WALNUT"}, {"codigo": "IFD3421TBL", "coleccion": "WALNUT"}, {"codigo": "IFD3422CHU", "coleccion": "WALNUT"}, {"codigo": "IFD3422CKT", "coleccion": "WALNUT"}, {"codigo": "IFD3422CST", "coleccion": "WALNUT"}, {"codigo": "IFD3422END", "coleccion": "WALNUT"}, {"codigo": "IFD3422SFT", "coleccion": "WALNUT"}, {"codigo": "IFD3422TBL", "coleccion": "WALNUT"}, {"codigo": "IFD3541CNS", "coleccion": "PRINCESS"}, {"codigo": "IFD3541CNSBK", "coleccion": "NEGRO MATE"}, {"codigo": "IFD3731BNKFLBT", "coleccion": "FORTE"}, {"codigo": "IFD3731BNKFLTP", "coleccion": "FORTE"}, {"codigo": "IFD3731BNKTWBT", "coleccion": "FORTE"}, {"codigo": "IFD3731BNKTWTP", "coleccion": "FORTE"}, {"codigo": "IFD3732BNKTWTP", "coleccion": "FORTE"}, {"codigo": "IFD3811CNS", "coleccion": "CAFÉ VERONA"}, {"codigo": "IFD3911CNS", "coleccion": "DARK VERONA"}, {"codigo": "IFD410CHAIR", "coleccion": "BONANZA"}, {"codigo": "IFD4221BAR", "coleccion": "BALAM"}, {"codigo": "IFD4221BEN", "coleccion": "BALAM"}, {"codigo": "IFD4221BFF", "coleccion": "BALAM"}, {"codigo": "IFD4221BISBA", "coleccion": "BALAM"}, {"codigo": "IFD4221BISTP", "coleccion": "BALAM"}, {"codigo": "IFD4221BKS", "coleccion": "BALAM"}, {"codigo": "IFD4221BVA", "coleccion": "BALAM"}, {"codigo": "IFD4221CAB", "coleccion": "BALAM"}, {"codigo": "IFD4221CHR", "coleccion": "BALAM"}, {"codigo": "IFD4221CHRGN", "coleccion": "BALAM"}, {"codigo": "IFD4221CHT", "coleccion": "BALAM"}, {"codigo": "IFD4221CHUBK", "coleccion": "BALAM"}, {"codigo": "IFD4221CHUBN", "coleccion": "BALAM"}, {"codigo": "IFD4221CHUGN", "coleccion": "BALAM"}, {"codigo": "IFD4221CHUIV", "coleccion": "BALAM"}, {"codigo": "IFD4221CKT", "coleccion": "BALAM"}, {"codigo": "IFD4221CNS", "coleccion": "BALAM"}, {"codigo": "IFD4221CNSBL", "coleccion": "ARCADIA BLUE"}, {"codigo": "IFD4221CNSGN", "coleccion": "ARCADIA VERDE"}, {"codigo": "IFD4221CST", "coleccion": "BALAM"}, {"codigo": "IFD4221CTB", "coleccion": "BALAM"}, {"codigo": "IFD4221DSK", "coleccion": "BALAM"}, {"codigo": "IFD4221DSR", "coleccion": "BALAM"}, {"codigo": "IFD4221END", "coleccion": "BALAM"}, {"codigo": "IFD4221GMC", "coleccion": "BALAM"}, {"codigo": "IFD4221HBDEK", "coleccion": "BALAM"}, {"codigo": "IFD4221HBDQE", "coleccion": "BALAM"}, {"codigo": "IFD4221KSL", "coleccion": "BALAM"}, {"codigo": "IFD4221MIR", "coleccion": "BALAM"}, {"codigo": "IFD4221NTS", "coleccion": "BALAM"}, {"codigo": "IFD4221PIR", "coleccion": "BALAM"}, {"codigo": "IFD4221PLTEK", "coleccion": "BALAM"}, {"codigo": "IFD4221PLTQE", "coleccion": "BALAM"}, {"codigo": "IFD4221RNDBA", "coleccion": "BALAM"}, {"codigo": "IFD4221RNDBA47", "coleccion": "BALAM"}, {"codigo": "IFD4221RNDTP", "coleccion": "BALAM"}, {"codigo": "IFD4221RNDTP47", "coleccion": "BALAM"}, {"codigo": "IFD4221STF80", "coleccion": "BALAM"}, {"codigo": "IFD4221STL24BN", "coleccion": "BALAM"}, {"codigo": "IFD4221STL24GN", "coleccion": "BALAM"}, {"codigo": "IFD4221STN", "coleccion": "BALAM"}, {"codigo": "IFD4221STN80", "coleccion": "BALAM"}, {"codigo": "IFD4221SVR", "coleccion": "BALAM"}, {"codigo": "IFD4221TBL", "coleccion": "BALAM"}, {"codigo": "IFD4222BEN", "coleccion": "BALAM"}, {"codigo": "IFD4222CHU", "coleccion": "BALAM"}, {"codigo": "IFD4222CKT", "coleccion": "BALAM"}, {"codigo": "IFD4222CNS", "coleccion": "BALAM"}, {"codigo": "IFD4222CST", "coleccion": "BALAM"}, {"codigo": "IFD4222END", "coleccion": "BALAM"}, {"codigo": "IFD4222SFT", "coleccion": "BALAM"}, {"codigo": "IFD4223BEN", "coleccion": "BALAM"}, {"codigo": "IFD4223CHR", "coleccion": "BALAM"}, {"codigo": "IFD4223CKT", "coleccion": "BALAM"}, {"codigo": "IFD4223CST", "coleccion": "BALAM"}, {"codigo": "IFD4223END", "coleccion": "BALAM"}, {"codigo": "IFD4223SFT", "coleccion": "BALAM"}, {"codigo": "IFD4224BEN", "coleccion": "BALAM"}, {"codigo": "IFD4224CHR", "coleccion": "BALAM"}, {"codigo": "IFD4226CHR", "coleccion": "BALAM"}, {"codigo": "IFD4321BAR", "coleccion": "WHITE BALAM"}, {"codigo": "IFD4321BEN", "coleccion": "WHITE BALAM"}, {"codigo": "IFD4321BFF", "coleccion": "WHITE BALAM"}, {"codigo": "IFD4321BISBA", "coleccion": "WHITE BALAM"}, {"codigo": "IFD4321BISTP", "coleccion": "WHITE BALAM"}, {"codigo": "IFD4321BKS", "coleccion": "WHITE BALAM"}, {"codigo": "IFD4321BVA", "coleccion": "WHITE BALAM"}, {"codigo": "IFD4321CAB", "coleccion": "WHITE BALAM"}, {"codigo": "IFD4321CHR", "coleccion": "WHITE BALAM"}, {"codigo": "IFD4321CHT", "coleccion": "WHITE BALAM"}, {"codigo": "IFD4321CHUBN", "coleccion": "WHITE BALAM"}, {"codigo": "IFD4321CHUGN", "coleccion": "WHITE BALAM"}, {"codigo": "IFD4321CHUIV", "coleccion": "WHITE BALAM"}, {"codigo": "IFD4321CKT", "coleccion": "WHITE BALAM"}, {"codigo": "IFD4321CNS", "coleccion": "WHITE BALAM"}, {"codigo": "IFD4321CST", "coleccion": "WHITE BALAM"}, {"codigo": "IFD4321CTB", "coleccion": "WHITE BALAM"}, {"codigo": "IFD4321DSK", "coleccion": "WHITE BALAM"}, {"codigo": "IFD4321DSR", "coleccion": "WHITE BALAM"}, {"codigo": "IFD4321END", "coleccion": "WHITE BALAM"}, {"codigo": "IFD4321GMC", "coleccion": "WHITE BALAM"}, {"codigo": "IFD4321HBDEK", "coleccion": "WHITE BALAM"}, {"codigo": "IFD4321HBDQE", "coleccion": "WHITE BALAM"}, {"codigo": "IFD4321KSL", "coleccion": "WHITE BALAM"}, {"codigo": "IFD4321MIR", "coleccion": "WHITE BALAM"}, {"codigo": "IFD4321NTS", "coleccion": "WHITE BALAM"}, {"codigo": "IFD4321PIR", "coleccion": "WHITE BALAM"}, {"codigo": "IFD4321PLTEK", "coleccion": "WHITE BALAM"}, {"codigo": "IFD4321PLTQE", "coleccion": "WHITE BALAM"}, {"codigo": "IFD4321RNDBA", "coleccion": "WHITE BALAM"}, {"codigo": "IFD4321RNDBA47", "coleccion": "WHITE BALAM"}, {"codigo": "IFD4321RNDTP", "coleccion": "WHITE BALAM"}, {"codigo": "IFD4321RNDTP47", "coleccion": "WHITE BALAM"}, {"codigo": "IFD4321STF80", "coleccion": "WHITE BALAM"}, {"codigo": "IFD4321STL24BN", "coleccion": "WHITE BALAM"}, {"codigo": "IFD4321STL24GN", "coleccion": "WHITE BALAM"}, {"codigo": "IFD4321STL24IV", "coleccion": "WHITE BALAM"}, {"codigo": "IFD4321STN", "coleccion": "WHITE BALAM"}, {"codigo": "IFD4321STN80", "coleccion": "WHITE BALAM"}, {"codigo": "IFD4321SVR", "coleccion": "WHITE BALAM"}, {"codigo": "IFD4321TBL", "coleccion": "WHITE BALAM"}, {"codigo": "IFD4322BEN", "coleccion": "WHITE BALAM"}, {"codigo": "IFD4322CKT", "coleccion": "WHITE BALAM"}, {"codigo": "IFD4322CNS", "coleccion": "WHITE BALAM"}, {"codigo": "IFD4322CST", "coleccion": "WHITE BALAM"}, {"codigo": "IFD4322END", "coleccion": "WHITE BALAM"}, {"codigo": "IFD4322SFT", "coleccion": "WHITE BALAM"}, {"codigo": "IFD4323BEN", "coleccion": "WHITE BALAM"}, {"codigo": "IFD4323CKT", "coleccion": "WHITE BALAM"}, {"codigo": "IFD4323CST", "coleccion": "WHITE BALAM"}, {"codigo": "IFD4323END", "coleccion": "WHITE BALAM"}, {"codigo": "IFD4323SFT", "coleccion": "WHITE BALAM"}, {"codigo": "IFD4324BEN", "coleccion": "WHITE BALAM"}, {"codigo": "IFD4324CHR", "coleccion": "WHITE BALAM"}, {"codigo": "IFD4351CHRTF", "coleccion": "MARQUEZ"}, {"codigo": "IFD4421BAR", "coleccion": "BLACK BALAM"}, {"codigo": "IFD4421BEN", "coleccion": "BLACK BALAM"}, {"codigo": "IFD4421BFF", "coleccion": "BLACK BALAM"}, {"codigo": "IFD4421BISBA", "coleccion": "BLACK BALAM"}, {"codigo": "IFD4421BISTP", "coleccion": "BLACK BALAM"}, {"codigo": "IFD4421BKS", "coleccion": "BLACK BALAM"}, {"codigo": "IFD4421CAB", "coleccion": "BLACK BALAM"}, {"codigo": "IFD4421CHR", "coleccion": "BLACK BALAM"}, {"codigo": "IFD4421CHT", "coleccion": "BLACK BALAM"}, {"codigo": "IFD4421CHUBN", "coleccion": "BLACK BALAM"}, {"codigo": "IFD4421CHUDS", "coleccion": "BLACK BALAM"}, {"codigo": "IFD4421CHUGN", "coleccion": "BLACK BALAM"}, {"codigo": "IFD4421CHUIV", "coleccion": "BLACK BALAM"}, {"codigo": "IFD4421CKT", "coleccion": "BLACK BALAM"}, {"codigo": "IFD4421CNS", "coleccion": "BLACK BALAM"}, {"codigo": "IFD4421CST", "coleccion": "BLACK BALAM"}, {"codigo": "IFD4421CTB", "coleccion": "BLACK BALAM"}, {"codigo": "IFD4421DSK", "coleccion": "BLACK BALAM"}, {"codigo": "IFD4421DSR", "coleccion": "BLACK BALAM"}, {"codigo": "IFD4421END", "coleccion": "BLACK BALAM"}, {"codigo": "IFD4421GMC", "coleccion": "BLACK BALAM"}, {"codigo": "IFD4421HBDEK", "coleccion": "BLACK BALAM"}, {"codigo": "IFD4421HBDQE", "coleccion": "BLACK BALAM"}, {"codigo": "IFD4421KSL", "coleccion": "BLACK BALAM"}, {"codigo": "IFD4421MIR", "coleccion": "BLACK BALAM"}, {"codigo": "IFD4421NTS", "coleccion": "BLACK BALAM"}, {"codigo": "IFD4421PIR", "coleccion": "BLACK BALAM"}, {"codigo": "IFD4421PLTEK", "coleccion": "BLACK BALAM"}, {"codigo": "IFD4421PLTQE", "coleccion": "BLACK BALAM"}, {"codigo": "IFD4421RNDBA", "coleccion": "BLACK BALAM"}, {"codigo": "IFD4421RNDBA47", "coleccion": "BLACK BALAM"}, {"codigo": "IFD4421RNDTP", "coleccion": "BLACK BALAM"}, {"codigo": "IFD4421RNDTP47", "coleccion": "BLACK BALAM"}, {"codigo": "IFD4421STF80", "coleccion": "BLACK BALAM"}, {"codigo": "IFD4421STL24BN", "coleccion": "BLACK BALAM"}, {"codigo": "IFD4421STL24GN", "coleccion": "BLACK BALAM"}, {"codigo": "IFD4421STN", "coleccion": "BLACK BALAM"}, {"codigo": "IFD4421STN80", "coleccion": "BLACK BALAM"}, {"codigo": "IFD4421SVR", "coleccion": "BLACK BALAM"}, {"codigo": "IFD4421TBL", "coleccion": "BLACK BALAM"}, {"codigo": "IFD4422BEN", "coleccion": "BLACK BALAM"}, {"codigo": "IFD4422CHU", "coleccion": "BLACK BALAM"}, {"codigo": "IFD4422CKT", "coleccion": "BLACK BALAM"}, {"codigo": "IFD4422CNS", "coleccion": "BLACK BALAM"}, {"codigo": "IFD4422CST", "coleccion": "BLACK BALAM"}, {"codigo": "IFD4422END", "coleccion": "BLACK BALAM"}, {"codigo": "IFD4422SFT", "coleccion": "BLACK BALAM"}, {"codigo": "IFD4423BEN", "coleccion": "BLACK BALAM"}, {"codigo": "IFD4423CHR", "coleccion": "BLACK BALAM"}, {"codigo": "IFD4423CKT", "coleccion": "BLACK BALAM"}, {"codigo": "IFD4423CST", "coleccion": "BLACK BALAM"}, {"codigo": "IFD4423END", "coleccion": "BLACK BALAM"}, {"codigo": "IFD4423SFT", "coleccion": "BLACK BALAM"}, {"codigo": "IFD4424BEN", "coleccion": "BLACK BALAM"}, {"codigo": "IFD4426CHR", "coleccion": "BLACK BALAM"}, {"codigo": "IFD4781CNSBN", "coleccion": "SILVER / TAMESIS"}, {"codigo": "IFD4781CNSWT", "coleccion": "MOKA WHITE / MOKA CAFÉ"}, {"codigo": "IFD4851CHT", "coleccion": "RARAMURI"}, {"codigo": "IFD4851CHUBN", "coleccion": "RARAMURI"}, {"codigo": "IFD4851CHUIV", "coleccion": "RARAMURI"}, {"codigo": "IFD4851CKT", "coleccion": "RARAMURI"}, {"codigo": "IFD4851CKTDL", "coleccion": "RARAMURI"}, {"codigo": "IFD4851CNS", "coleccion": "RARAMURI"}, {"codigo": "IFD4851CST", "coleccion": "RARAMURI"}, {"codigo": "IFD4851DSR", "coleccion": "RARAMURI"}, {"codigo": "IFD4851END", "coleccion": "RARAMURI"}, {"codigo": "IFD4851HBDEK", "coleccion": "RARAMURI"}, {"codigo": "IFD4851HBDQE", "coleccion": "RARAMURI"}, {"codigo": "IFD4851MIR", "coleccion": "RARAMURI"}, {"codigo": "IFD4851NTS", "coleccion": "RARAMURI"}, {"codigo": "IFD4851PLTEK", "coleccion": "RARAMURI"}, {"codigo": "IFD4851PLTQE", "coleccion": "RARAMURI"}, {"codigo": "IFD4851RNDBA", "coleccion": "RARAMURI"}, {"codigo": "IFD4851RNDTP", "coleccion": "RARAMURI"}, {"codigo": "IFD4851SFT", "coleccion": "RARAMURI"}, {"codigo": "IFD4851TBLBA", "coleccion": "RARAMURI"}, {"codigo": "IFD4851TBLTP", "coleccion": "RARAMURI"}, {"codigo": "IFD4852CHUBN", "coleccion": "RARAMURI"}, {"codigo": "IFD4852CHUIV", "coleccion": "RARAMURI"}, {"codigo": "IFD4853CKT", "coleccion": "RARAMURI"}, {"codigo": "IFD4853CST", "coleccion": "RARAMURI"}, {"codigo": "IFD4853END", "coleccion": "RARAMURI"}, {"codigo": "IFD5201BEN", "coleccion": "URBAN ART"}, {"codigo": "IFD5201CHR", "coleccion": "URBAN ART"}, {"codigo": "IFD5201TBLBA", "coleccion": "URBAN ART"}, {"codigo": "IFD5201TBLTP", "coleccion": "URBAN ART"}, {"codigo": "IFD5721CHR", "coleccion": "XELHA"}, {"codigo": "IFD5721CHU", "coleccion": "XELHA"}, {"codigo": "IFD5721CNS", "coleccion": "XELHA"}, {"codigo": "IFD5721CNSBL", "coleccion": "ARCADIA BLUE"}, {"codigo": "IFD5721CNSGN", "coleccion": "ARCADIA VERDE"}, {"codigo": "IFD5721TBL", "coleccion": "XELHA"}, {"codigo": "IFD5821CHU", "coleccion": "ZAPHIRO"}, {"codigo": "IFD5821DSK", "coleccion": "FORGE"}, {"codigo": "IFD5821TBLBA", "coleccion": "FORGE"}, {"codigo": "IFD5821TBLTP", "coleccion": "FORGE"}, {"codigo": "IFD5822CHU", "coleccion": "ZAPHIRO"}, {"codigo": "IFD5823CHUBG", "coleccion": "ZAPHIRO"}, {"codigo": "IFD5823CHUBL", "coleccion": "ZAPHIRO"}, {"codigo": "IFD5824CHUBG", "coleccion": "ZAPHIRO"}, {"codigo": "IFD5824CHUBL", "coleccion": "ZAPHIRO"}, {"codigo": "IFD5826CHU", "coleccion": "NEGRO"}, {"codigo": "IFD5951CHUBN", "coleccion": "ZAPHIRO"}, {"codigo": "IFD5951CHUIV", "coleccion": "ZAPHIRO"}, {"codigo": "IFD5951CNS", "coleccion": "ZAPHIRO"}, {"codigo": "IFD5951RNDBA", "coleccion": "ZAPHIRO"}, {"codigo": "IFD5951RNDTP", "coleccion": "ZAPHIRO"}, {"codigo": "IFD5951TBLBA", "coleccion": "ZAPHIRO"}, {"codigo": "IFD5951TBLTP", "coleccion": "ZAPHIRO"}, {"codigo": "IFD5952CHUBN", "coleccion": "ZAPHIRO"}, {"codigo": "IFD5952CHUIV", "coleccion": "ZAPHIRO"}, {"codigo": "IFD5952CKT", "coleccion": "ZAPHIRO"}, {"codigo": "IFD5952CST", "coleccion": "ZAPHIRO"}, {"codigo": "IFD5952END", "coleccion": "ZAPHIRO"}, {"codigo": "IFD5953CHU", "coleccion": "ZAPHIRO"}, {"codigo": "IFD5953CKT", "coleccion": "ZAPHIRO"}, {"codigo": "IFD5953CST", "coleccion": "ZAPHIRO"}, {"codigo": "IFD5953END", "coleccion": "ZAPHIRO"}, {"codigo": "IFD5953SFT", "coleccion": "ZAPHIRO"}, {"codigo": "IFD6131CHT", "coleccion": "MOKA WHITE"}, {"codigo": "IFD6131DSR", "coleccion": "MOKA WHITE"}, {"codigo": "IFD6131HBDEK", "coleccion": "MOKA WHITE"}, {"codigo": "IFD6131HBDQE", "coleccion": "MOKA WHITE"}, {"codigo": "IFD6131MIR", "coleccion": "MOKA WHITE"}, {"codigo": "IFD6131NTS", "coleccion": "MOKA WHITE"}, {"codigo": "IFD6131PLTEK", "coleccion": "MOKA WHITE"}, {"codigo": "IFD6131PLTQE", "coleccion": "MOKA WHITE"}, {"codigo": "IFD6212CHT", "coleccion": "NATURAL PAROTA"}, {"codigo": "IFD6212DSR", "coleccion": "NATURAL PAROTA"}, {"codigo": "IFD6212HBDEK", "coleccion": "NATURAL PAROTA"}, {"codigo": "IFD6212HBDQE", "coleccion": "NATURAL PAROTA"}, {"codigo": "IFD6212MIR", "coleccion": "NATURAL PAROTA"}, {"codigo": "IFD6212NTS", "coleccion": "NATURAL PAROTA"}, {"codigo": "IFD6212PLTCK", "coleccion": "NATURAL PAROTA"}, {"codigo": "IFD6212PLTEK", "coleccion": "NATURAL PAROTA"}, {"codigo": "IFD6212PLTQE", "coleccion": "NATURAL PAROTA"}, {"codigo": "IFD6231CHT", "coleccion": "PAROTA"}, {"codigo": "IFD6231DSR", "coleccion": "PAROTA"}, {"codigo": "IFD6231HBDEK", "coleccion": "PAROTA"}, {"codigo": "IFD6231HBDQE", "coleccion": "PAROTA"}, {"codigo": "IFD6231MIR", "coleccion": "PAROTA"}, {"codigo": "IFD6231NTS", "coleccion": "PAROTA"}, {"codigo": "IFD6231PLTEK", "coleccion": "PAROTA"}, {"codigo": "IFD6231PLTQE", "coleccion": "PAROTA"}, {"codigo": "IFD6471BST24", "coleccion": "SILVER"}, {"codigo": "IFD6471BST30", "coleccion": "SILVER"}, {"codigo": "IFD6471CHR", "coleccion": "SILVER"}, {"codigo": "IFD6471CHU", "coleccion": "SILVER"}, {"codigo": "IFD6471CKT", "coleccion": "SILVER"}, {"codigo": "IFD6471CST", "coleccion": "SILVER"}, {"codigo": "IFD6471END", "coleccion": "SILVER"}, {"codigo": "IFD6471RNDBA", "coleccion": "SILVER"}, {"codigo": "IFD6471RNDTP", "coleccion": "SILVER"}, {"codigo": "IFD6471TBLBA", "coleccion": "SILVER"}, {"codigo": "IFD6471TBLTP", "coleccion": "SILVER"}, {"codigo": "IFD6472CHU", "coleccion": "SILVER"}, {"codigo": "IFD6472RNDTP", "coleccion": "SILVER"}, {"codigo": "IFD6473CHU", "coleccion": "SILVER"}, {"codigo": "IFD6474CHU", "coleccion": "SILVER"}, {"codigo": "IFD6476CHU", "coleccion": "SILVER"}, {"codigo": "IFD6531CKTBK", "coleccion": "DARK MEZQUITE"}, {"codigo": "IFD6531CKTBN", "coleccion": "BROWN OSLO"}, {"codigo": "IFD6531CNSBL", "coleccion": "DARK BLUE OSLO"}, {"codigo": "IFD6531CNSBN", "coleccion": "BROWN OSLO"}, {"codigo": "IFD6531CNSWT", "coleccion": "WHITE OSLO"}, {"codigo": "IFD6531CSTBK", "coleccion": "DARK MEZQUITE"}, {"codigo": "IFD6531CSTBN", "coleccion": "BROWN OSLO"}, {"codigo": "IFD6531ENDBK", "coleccion": "DARK MEZQUITE"}, {"codigo": "IFD6531ENDBN", "coleccion": "BROWN OSLO"}, {"codigo": "IFD6531SFTBK", "coleccion": "DARK MEZQUITE"}, {"codigo": "IFD6531SFTBN", "coleccion": "BROWN OSLO"}, {"codigo": "IFD6551CHR", "coleccion": "LOFT BROWN"}, {"codigo": "IFD6621BKS", "coleccion": "MEZQUITE"}, {"codigo": "IFD6621CHT", "coleccion": "MEZQUITE"}, {"codigo": "IFD6621CHU", "coleccion": "MEZQUITE"}, {"codigo": "IFD6621CST", "coleccion": "MEZQUITE"}, {"codigo": "IFD6621DSK", "coleccion": "MEZQUITE"}, {"codigo": "IFD6621EFP", "coleccion": "MEZQUITE"}, {"codigo": "IFD6621EFP70", "coleccion": "MEZQUITE"}, {"codigo": "IFD6621END", "coleccion": "MEZQUITE"}, {"codigo": "IFD6621HBDEK", "coleccion": "MEZQUITE"}, {"codigo": "IFD6621HBDQE", "coleccion": "MEZQUITE"}, {"codigo": "IFD6621KSL", "coleccion": "MEZQUITE"}, {"codigo": "IFD6621PLTEK", "coleccion": "MEZQUITE"}, {"codigo": "IFD6621PLTQE", "coleccion": "MEZQUITE"}, {"codigo": "IFD6621STF", "coleccion": "MEZQUITE"}, {"codigo": "IFD6622CHT", "coleccion": "MEZQUITE"}, {"codigo": "IFD6622CHU", "coleccion": "MEZQUITE"}, {"codigo": "IFD6622CHUGN", "coleccion": "MEZQUITE"}, {"codigo": "IFD6622DSR", "coleccion": "MEZQUITE"}, {"codigo": "IFD6622HBDEK", "coleccion": "MEZQUITE"}, {"codigo": "IFD6622HBDQE", "coleccion": "MEZQUITE"}, {"codigo": "IFD6622MIR", "coleccion": "MEZQUITE"}, {"codigo": "IFD6622PLTEK", "coleccion": "MEZQUITE"}, {"codigo": "IFD6622PLTQE", "coleccion": "MEZQUITE"}, {"codigo": "IFD6622TBL", "coleccion": "MEZQUITE"}, {"codigo": "IFD6631CHU", "coleccion": "DARK MEZQUITE"}, {"codigo": "IFD6631STF", "coleccion": "DARK MEZQUITE"}, {"codigo": "IFD6632CHU", "coleccion": "DARK MEZQUITE"}, {"codigo": "IFD6632CHUGN", "coleccion": "DARK MEZQUITE"}, {"codigo": "IFD6721CHT", "coleccion": "Balam"}, {"codigo": "IFD6721DSR", "coleccion": "Balam"}, {"codigo": "IFD6721HBDEK", "coleccion": "Balam"}, {"codigo": "IFD6721HBDQE", "coleccion": "Balam"}, {"codigo": "IFD6721MIR", "coleccion": "Balam"}, {"codigo": "IFD6721NTS", "coleccion": "Balam"}, {"codigo": "IFD6721PLTEK", "coleccion": "Balam"}, {"codigo": "IFD6721PLTQE", "coleccion": "Balam"}, {"codigo": "IFD6731CHT", "coleccion": "ROOTS"}, {"codigo": "IFD6731DSR", "coleccion": "ROOTS"}, {"codigo": "IFD6731HBDEK", "coleccion": "ROOTS"}, {"codigo": "IFD6731HBDQE", "coleccion": "ROOTS"}, {"codigo": "IFD6731MIR", "coleccion": "ROOTS"}, {"codigo": "IFD6731NTS", "coleccion": "ROOTS"}, {"codigo": "IFD6731PLTEK", "coleccion": "ROOTS"}, {"codigo": "IFD6731PLTQE", "coleccion": "ROOTS"}, {"codigo": "IFD7331CHR", "coleccion": "CAFÉ ARUBA"}, {"codigo": "IFD7331CHUBG", "coleccion": "ARUBA NATURAL"}, {"codigo": "IFD7781CKT", "coleccion": "NA"}, {"codigo": "IFD7781CNS", "coleccion": "BLACKBURN"}, {"codigo": "IFD8351CKTBL", "coleccion": "Parota Epoxy"}, {"codigo": "IFD8351CKTOR", "coleccion": "Parota Epoxy"}, {"codigo": "IFD8351CSTBL", "coleccion": "Parota Epoxy"}, {"codigo": "IFD8351CSTOR", "coleccion": "Parota Epoxy"}, {"codigo": "IFD8351ENDBL", "coleccion": "Parota Epoxy"}, {"codigo": "IFD8351ENDOR", "coleccion": "Parota Epoxy"}, {"codigo": "IFD8351SFTBL", "coleccion": "Parota Epoxy"}, {"codigo": "IFD8351SFTOR", "coleccion": "Parota Epoxy"}, {"codigo": "IFD8521CNSBK", "coleccion": "NA"}, {"codigo": "IFD8521CNSBL", "coleccion": "NA"}, {"codigo": "IFD8521CNSBN", "coleccion": "SILVER"}, {"codigo": "IFD8521CNSWT", "coleccion": "WHITE OSLO"}, {"codigo": "IFD865BS24", "coleccion": "PAROTA"}, {"codigo": "IFD865BS30", "coleccion": "PAROTA"}, {"codigo": "IFD865CHAIR", "coleccion": "PAROTA"}, {"codigo": "IFD8661STN93", "coleccion": "PAROTA"}, {"codigo": "IFD866BAR-B", "coleccion": "PAROTA"}, {"codigo": "IFD866BAR-T", "coleccion": "PAROTA"}, {"codigo": "IFD866BENCH", "coleccion": "PAROTA"}, {"codigo": "IFD866BKCS-70", "coleccion": "PAROTA"}, {"codigo": "IFD866BS2430", "coleccion": "PAROTA"}, {"codigo": "IFD866CHAIR-S", "coleccion": "PAROTA"}, {"codigo": "IFD866CHEST", "coleccion": "PAROTA"}, {"codigo": "IFD866CKTL", "coleccion": "PAROTA"}, {"codigo": "IFD866CONS", "coleccion": "PAROTA"}, {"codigo": "IFD866CST", "coleccion": "PAROTA"}, {"codigo": "IFD866DESK", "coleccion": "PAROTA"}, {"codigo": "IFD866DSR", "coleccion": "PAROTA"}, {"codigo": "IFD866END", "coleccion": "PAROTA"}, {"codigo": "IFD866HDBD-EK1", "coleccion": "PAROTA"}, {"codigo": "IFD866HDBD-Q1", "coleccion": "PAROTA"}, {"codigo": "IFD866ISLAND", "coleccion": "PAROTA"}, {"codigo": "IFD866MIRR", "coleccion": "PAROTA"}, {"codigo": "IFD866NTST", "coleccion": "PAROTA"}, {"codigo": "IFD866PLTFRM-CK", "coleccion": "PAROTA"}, {"codigo": "IFD866PLTFRM-EK", "coleccion": "PAROTA"}, {"codigo": "IFD866PLTFRM-Q", "coleccion": "PAROTA"}, {"codigo": "IFD866SOFA", "coleccion": "PAROTA"}, {"codigo": "IFD866STAND-50", "coleccion": "PAROTA"}, {"codigo": "IFD866STAND-60", "coleccion": "PAROTA"}, {"codigo": "IFD866STAND-70", "coleccion": "PAROTA"}, {"codigo": "IFD866TABLE-B", "coleccion": "PAROTA"}, {"codigo": "IFD866TABLE-T", "coleccion": "PAROTA"}, {"codigo": "IFD867CKTL", "coleccion": "PAROTA"}, {"codigo": "IFD867CST", "coleccion": "PAROTA"}, {"codigo": "IFD867END", "coleccion": "PAROTA"}, {"codigo": "IFD867SOFA", "coleccion": "PAROTA"}, {"codigo": "IFD867STAND-60", "coleccion": "PAROTA"}, {"codigo": "IFD867STAND-70", "coleccion": "PAROTA"}, {"codigo": "IFD8681BAR", "coleccion": "NATURAL PAROTA"}, {"codigo": "IFD8681BKS", "coleccion": "NATURAL PAROTA"}, {"codigo": "IFD8681CAB", "coleccion": "NATURAL PAROTA"}, {"codigo": "IFD8681CHR", "coleccion": "NATURAL PAROTA"}, {"codigo": "IFD8681CHT", "coleccion": "NATURAL PAROTA"}, {"codigo": "IFD8681CKT", "coleccion": "NATURAL PAROTA"}, {"codigo": "IFD8681CKTDL", "coleccion": "NATURAL PAROTA"}, {"codigo": "IFD8681CKTSQ", "coleccion": "NATURAL PAROTA"}, {"codigo": "IFD8681CNS", "coleccion": "NATURAL PAROTA"}, {"codigo": "IFD8681CST", "coleccion": "NATURAL PAROTA"}, {"codigo": "IFD8681DSK", "coleccion": "NATURAL PAROTA"}, {"codigo": "IFD8681DSR", "coleccion": "NATURAL PAROTA"}, {"codigo": "IFD8681EFP70", "coleccion": "NATURAL PAROTA"}, {"codigo": "IFD8681EFP93", "coleccion": "NATURAL PAROTA"}, {"codigo": "IFD8681END", "coleccion": "NATURAL PAROTA"}, {"codigo": "IFD8681HBDEK1", "coleccion": "NATURAL PAROTA"}, {"codigo": "IFD8681HBDQE1", "coleccion": "NATURAL PAROTA"}, {"codigo": "IFD8681MIR", "coleccion": "NATURAL PAROTA"}, {"codigo": "IFD8681NTS", "coleccion": "NATURAL PAROTA"}, {"codigo": "IFD8681PLTCK", "coleccion": "NATURAL PAROTA"}, {"codigo": "IFD8681PLTEK", "coleccion": "NATURAL PAROTA"}, {"codigo": "IFD8681PLTQE", "coleccion": "NATURAL PAROTA"}, {"codigo": "IFD8681RNDBA", "coleccion": "NATURAL PAROTA"}, {"codigo": "IFD8681RNDTP", "coleccion": "NATURAL PAROTA"}, {"codigo": "IFD8681SFT", "coleccion": "NATURAL PAROTA"}, {"codigo": "IFD8681STN70", "coleccion": "NATURAL PAROTA"}, {"codigo": "IFD8681STN80", "coleccion": "NATURAL PAROTA"}, {"codigo": "IFD8681STN88", "coleccion": "NATURAL PAROTA"}, {"codigo": "IFD8681STN93", "coleccion": "NATURAL PAROTA"}, {"codigo": "IFD8681TBLBA", "coleccion": "NA"}, {"codigo": "IFD8681TBLTP", "coleccion": "NATURAL PAROTA"}, {"codigo": "IFD8682BKS", "coleccion": "NATURAL PAROTA"}, {"codigo": "IFD8682CHR", "coleccion": "NATURAL PAROTA"}, {"codigo": "IFD8682CHU", "coleccion": "CAFÉ SUGAR"}, {"codigo": "IFD8682EFP", "coleccion": "CAFÉ SUGAR"}, {"codigo": "IFD8682TBLBA", "coleccion": "NA"}, {"codigo": "IFD8682TBLTP", "coleccion": "NATURAL PAROTA"}, {"codigo": "IFD8683CHR", "coleccion": "NATURAL PAROTA"}, {"codigo": "IFD8683CHU", "coleccion": "CAFÉ SUGAR"}, {"codigo": "IFD880CKTL", "coleccion": "VIVO"}, {"codigo": "IFD880OC17", "coleccion": "VIVO"}, {"codigo": "IFD880OC22", "coleccion": "VIVO"}, {"codigo": "IFD880SOFA", "coleccion": "VIVO"}, {"codigo": "IFD8841CHR", "coleccion": "RIVERWOOD"}, {"codigo": "IFD8841CHU", "coleccion": "Parota III"}, {"codigo": "IFD8841CKT", "coleccion": "Parota III"}, {"codigo": "IFD8841CST", "coleccion": "RIVERWOOD"}, {"codigo": "IFD8841END", "coleccion": "RIVERWOOD"}, {"codigo": "IFD8841SFT", "coleccion": "Parota III"}, {"codigo": "IFD8841TBLBA", "coleccion": "Parota III"}, {"codigo": "IFD8841TBLTP", "coleccion": "Parota III"}, {"codigo": "IFD9071CNS", "coleccion": "REGAL"}, {"codigo": "IFD9131CNS", "coleccion": "SILVER-NASHVILLE"}, {"codigo": "IFD-EFP26", "coleccion": "NA"}, {"codigo": "IFD-EFP42", "coleccion": "NA"}, {"codigo": "IFD-EFP50", "coleccion": "NA"}, {"codigo": "IFD-EFP50LG", "coleccion": "NA"}, {"codigo": "IFD-EFP50-LOG", "coleccion": "NA"}, {"codigo": "IRG1181BKS", "coleccion": "MOKA-DARK MOKA"}, {"codigo": "IRG1181CNS", "coleccion": "MOKA-DARK MOKA"}, {"codigo": "IRG1181PIR", "coleccion": "MOKA-DARK MOKA"}, {"codigo": "IRG1182BKS", "coleccion": "MOKA-DARK MOKA"}, {"codigo": "IRG4511BKSBK", "coleccion": "BLANCO CANOE"}, {"codigo": "IRG4511BKSBN", "coleccion": "BLANCO CANOE"}, {"codigo": "IRG4511CKTBK", "coleccion": "BLANCO CANOE"}, {"codigo": "IRG4511CKTBN", "coleccion": "BLANCO CANOE"}, {"codigo": "IRG4511CNSBK", "coleccion": "BLANCO CANOE"}, {"codigo": "IRG4511CNSBN", "coleccion": "BLANCO CANOE"}, {"codigo": "IRG4511CNSWT", "coleccion": "BLANCO CANOE"}, {"codigo": "IRG4511CSTBK", "coleccion": "BLANCO CANOE"}, {"codigo": "IRG4511CSTBN", "coleccion": "BLANCO CANOE"}, {"codigo": "IRG4511DSKBK", "coleccion": "BLANCO CANOE"}, {"codigo": "IRG4511DSKBN", "coleccion": "BLANCO CANOE"}, {"codigo": "IRG4511ENDBK", "coleccion": "BLANCO CANOE"}, {"codigo": "IRG4511ENDBN", "coleccion": "BLANCO CANOE"}, {"codigo": "IRG4511ENDWT", "coleccion": "BLANCO CANOE"}, {"codigo": "IRG4511SFTBK", "coleccion": "BLANCO CANOE"}, {"codigo": "IRG4511SFTBN", "coleccion": "BLANCO CANOE"}, {"codigo": "IRG4511STN80BK", "coleccion": "BLANCO CANOE"}, {"codigo": "IRG4511STN80BN", "coleccion": "BLANCO CANOE"}, {"codigo": "IRG4512BKSBK", "coleccion": "BLANCO CANOE"}, {"codigo": "IRG4512BKSBN", "coleccion": "BLANCO CANOE"}, {"codigo": "IUM1099-CLS-L21", "coleccion": "BLANCO CANOE"}, {"codigo": "IUM1099-RCL-L21", "coleccion": "BLANCO CANOE"}, {"codigo": "IUM1099-RSF-L21", "coleccion": "BLANCO CANOE"}, {"codigo": "IUM1972-LSF-L22", "coleccion": "BLANCO CANOE"}, {"codigo": "IUM1972-RCL-L22", "coleccion": "BLANCO CANOE"}, {"codigo": "IUM1972-RLV-L22", "coleccion": "BLANCO CANOE"}, {"codigo": "IUM2018-CLS-L23", "coleccion": "BLANCO CANOE"}, {"codigo": "IUM2018-CLS-L25", "coleccion": "NA"}, {"codigo": "IUM2018-RCL-L23", "coleccion": "BLANCO CANOE"}, {"codigo": "IUM2018-RCL-L25", "coleccion": "NA"}, {"codigo": "IUM2018-RSF-L23", "coleccion": "BLANCO CANOE"}, {"codigo": "IUM2018-RSF-L25", "coleccion": "NA"}, {"codigo": "IUM2068-CLS-L24", "coleccion": "BLANCO CANOE"}, {"codigo": "IUM2068-RCL-L24", "coleccion": "BLANCO CANOE"}, {"codigo": "IUM2068-RSF-L24", "coleccion": "BLANCO CANOE"}, {"codigo": "IUM3050-CLS-L02", "coleccion": "BLANCO CANOE"}, {"codigo": "IUM3050-RCL-L02", "coleccion": "BLANCO CANOE"}, {"codigo": "IUM3050-RSF-L02", "coleccion": "BLANCO CANOE"}, {"codigo": "IUM3183-CLS-L01", "coleccion": "BLANCO CANOE"}, {"codigo": "IUM3183-RCL-L01", "coleccion": "BLANCO CANOE"}, {"codigo": "IUM3183-RSF-L01", "coleccion": "BLANCO CANOE"}, {"codigo": "IUM3190-RCL-L03", "coleccion": "BLANCO CANOE"}, {"codigo": "IUM3190-RLV-L03", "coleccion": "BLANCO CANOE"}, {"codigo": "IUM3190-RSF-L03", "coleccion": "BLANCO CANOE"}, {"codigo": "IUM3191-RCL-L03", "coleccion": "BLANCO CANOE"}, {"codigo": "IUM6102-CLS-L26", "coleccion": "BLANCO CANOE"}, {"codigo": "IUM6102-CLS-L27", "coleccion": "BLANCO CANOE"}, {"codigo": "IUM6102-LSF-L26", "coleccion": "BLANCO CANOE"}, {"codigo": "IUM6102-LSF-L27", "coleccion": "BLANCO CANOE"}, {"codigo": "IUM6102-RCL-L26", "coleccion": "BLANCO CANOE"}, {"codigo": "IUM6102-RCL-L27", "coleccion": "BLANCO CANOE"}, {"codigo": "IUP117-ACH-232", "coleccion": "NATURAL TECA"}, {"codigo": "IUP117-LOV-232", "coleccion": "NATURAL TECA"}, {"codigo": "IUP117-SOF-232", "coleccion": "NATURAL TECA"}, {"codigo": "IUP124-ACH-184", "coleccion": "REGAL"}, {"codigo": "IUP124-LOV-184", "coleccion": "REGAL"}, {"codigo": "IUP124-SOF-184", "coleccion": "REGAL"}, {"codigo": "IUP132-ACH-101", "coleccion": "NA"}, {"codigo": "IUP132-ACH-111", "coleccion": "NA"}, {"codigo": "IUP132-ACH-121", "coleccion": "NA"}, {"codigo": "IUP132-ACH-131", "coleccion": "NA"}, {"codigo": "IUP132-ACH-161", "coleccion": "NA"}, {"codigo": "IUP132-ACH-202", "coleccion": "NA"}, {"codigo": "IUP132-ACH-210", "coleccion": "NA"}, {"codigo": "IUP132-ACH-212", "coleccion": "NA"}, {"codigo": "IUP132-ACH-216", "coleccion": "NA"}, {"codigo": "IUP132-ACH-221", "coleccion": "NA"}, {"codigo": "IUP221-ACH-101", "coleccion": "CAFÉ ARUBA"}, {"codigo": "IUP221-ACH-111", "coleccion": "CAFÉ ARUBA"}, {"codigo": "IUP221-ACH-121", "coleccion": "CAFÉ ARUBA"}, {"codigo": "IUP221-ACH-151", "coleccion": "CAFÉ ARUBA"}, {"codigo": "IUP221-ACH-152", "coleccion": "CAFÉ ARUBA"}, {"codigo": "IUP221-ACH-161", "coleccion": "CAFÉ ARUBA"}, {"codigo": "IUP221-ACH-202", "coleccion": "CAFÉ ARUBA"}, {"codigo": "IUP221-ACH-210", "coleccion": "CAFÉ ARUBA"}, {"codigo": "IUP221-ACH-212", "coleccion": "CAFÉ ARUBA"}, {"codigo": "IUP222-ACH-101", "coleccion": "NA"}, {"codigo": "IUP222-ACH-202", "coleccion": "NA"}, {"codigo": "IUP222-ACH-210", "coleccion": "NA"}, {"codigo": "IUP222-ACH-212", "coleccion": "NA"}, {"codigo": "IUP222-ACH-214", "coleccion": "NA"}, {"codigo": "IUP222-ACH-216", "coleccion": "NA"}, {"codigo": "IUP222-BST24-161", "coleccion": "NA"}, {"codigo": "IUP222-BST24-214", "coleccion": "NA"}, {"codigo": "IUP222-BST30-161", "coleccion": "NA"}, {"codigo": "IUP222-BST30-214", "coleccion": "NA"}, {"codigo": "IUP298-ACH-111", "coleccion": "ARUBA NATURAL"}, {"codigo": "IUP298-ACH-121", "coleccion": "ARUBA NATURAL"}, {"codigo": "IUP298-ACH-131", "coleccion": "ARUBA NATURAL"}, {"codigo": "IUP298-ACH-151", "coleccion": "ARUBA NATURAL"}, {"codigo": "IUP298-ACH-152", "coleccion": "ARUBA NATURAL"}, {"codigo": "IUP298-ACH-161", "coleccion": "ARUBA NATURAL"}, {"codigo": "IUP298-ACH-202", "coleccion": "ARUBA NATURAL"}, {"codigo": "IUP298-ACH-210", "coleccion": "ARUBA NATURAL"}, {"codigo": "IUP298-ACH-212", "coleccion": "ARUBA NATURAL"}, {"codigo": "IUP298-ACH-231", "coleccion": "ARUBA NATURAL"}, {"codigo": "IUP298-ALC-111", "coleccion": "ARUBA NATURAL"}, {"codigo": "IUP298-ALC-121", "coleccion": "ARUBA NATURAL"}, {"codigo": "IUP298-ALC-131", "coleccion": "ARUBA NATURAL"}, {"codigo": "IUP298-ALC-151", "coleccion": "ARUBA NATURAL"}, {"codigo": "IUP298-ALC-152", "coleccion": "ARUBA NATURAL"}, {"codigo": "IUP298-ALC-161", "coleccion": "ARUBA NATURAL"}, {"codigo": "IUP298-ALC-210", "coleccion": "ARUBA NATURAL"}, {"codigo": "IUP298-ALC-212", "coleccion": "ARUBA NATURAL"}, {"codigo": "IUP298-CSE-LF-111", "coleccion": "ARUBA NATURAL"}, {"codigo": "IUP298-CSE-LF-131", "coleccion": "ARUBA NATURAL"}, {"codigo": "IUP298-CSE-LF-151", "coleccion": "ARUBA NATURAL"}, {"codigo": "IUP298-CSE-LF-152", "coleccion": "ARUBA NATURAL"}, {"codigo": "IUP298-CSE-LF-161", "coleccion": "ARUBA NATURAL"}, {"codigo": "IUP298-CSE-LF-210", "coleccion": "ARUBA NATURAL"}, {"codigo": "IUP298-CSE-LF-212", "coleccion": "ARUBA NATURAL"}, {"codigo": "IUP298-CSE-RT-111", "coleccion": "ARUBA NATURAL"}, {"codigo": "IUP298-CSE-RT-121", "coleccion": "ARUBA NATURAL"}, {"codigo": "IUP298-CSE-RT-131", "coleccion": "ARUBA NATURAL"}, {"codigo": "IUP298-CSE-RT-151", "coleccion": "ARUBA NATURAL"}, {"codigo": "IUP298-CSE-RT-152", "coleccion": "ARUBA NATURAL"}, {"codigo": "IUP298-CSE-RT-161", "coleccion": "ARUBA NATURAL"}, {"codigo": "IUP298-CSE-RT-210", "coleccion": "ARUBA NATURAL"}, {"codigo": "IUP298-CSE-RT-212", "coleccion": "ARUBA NATURAL"}, {"codigo": "IUP298-LOV-111", "coleccion": "ARUBA NATURAL"}, {"codigo": "IUP298-LOV-121", "coleccion": "ARUBA NATURAL"}, {"codigo": "IUP298-LOV-131", "coleccion": "ARUBA NATURAL"}, {"codigo": "IUP298-LOV-131-A", "coleccion": "ARUBA NATURAL"}, {"codigo": "IUP298-LOV-151", "coleccion": "ARUBA NATURAL"}, {"codigo": "IUP298-LOV-151-A", "coleccion": "ARUBA NATURAL"}, {"codigo": "IUP298-LOV-152", "coleccion": "ARUBA NATURAL"}, {"codigo": "IUP298-LOV-152-A", "coleccion": "ARUBA NATURAL"}, {"codigo": "IUP298-LOV-161", "coleccion": "ARUBA NATURAL"}, {"codigo": "IUP298-LOV-161-A", "coleccion": "ARUBA NATURAL"}, {"codigo": "IUP298-LOV-202", "coleccion": "ARUBA NATURAL"}, {"codigo": "IUP298-LOV-210", "coleccion": "ARUBA NATURAL"}, {"codigo": "IUP298-LOV-212", "coleccion": "ARUBA NATURAL"}, {"codigo": "IUP298-LOV-231", "coleccion": "ARUBA NATURAL"}, {"codigo": "IUP298-LOV-LF-111", "coleccion": "ARUBA NATURAL"}, {"codigo": "IUP298-LOV-LF-121", "coleccion": "ARUBA NATURAL"}, {"codigo": "IUP298-LOV-LF-131", "coleccion": "ARUBA NATURAL"}, {"codigo": "IUP298-LOV-LF-151", "coleccion": "ARUBA NATURAL"}, {"codigo": "IUP298-LOV-LF-152", "coleccion": "ARUBA NATURAL"}, {"codigo": "IUP298-LOV-LF-161", "coleccion": "ARUBA NATURAL"}, {"codigo": "IUP298-LOV-LF-210", "coleccion": "ARUBA NATURAL"}, {"codigo": "IUP298-LOV-LF-212", "coleccion": "ARUBA NATURAL"}, {"codigo": "IUP298-LOV-RT-111", "coleccion": "ARUBA NATURAL"}, {"codigo": "IUP298-LOV-RT-111-A", "coleccion": "ARUBA NATURAL"}, {"codigo": "IUP298-LOV-RT-121", "coleccion": "ARUBA NATURAL"}, {"codigo": "IUP298-LOV-RT-131", "coleccion": "ARUBA NATURAL"}, {"codigo": "IUP298-LOV-RT-131-A", "coleccion": "ARUBA NATURAL"}, {"codigo": "IUP298-LOV-RT-151", "coleccion": "ARUBA NATURAL"}, {"codigo": "IUP298-LOV-RT-151-A", "coleccion": "ARUBA NATURAL"}, {"codigo": "IUP298-LOV-RT-152", "coleccion": "ARUBA NATURAL"}, {"codigo": "IUP298-LOV-RT-152-A", "coleccion": "ARUBA NATURAL"}, {"codigo": "IUP298-LOV-RT-161", "coleccion": "ARUBA NATURAL"}, {"codigo": "IUP298-LOV-RT-161-A", "coleccion": "ARUBA NATURAL"}, {"codigo": "IUP298-LOV-RT-210", "coleccion": "ARUBA NATURAL"}, {"codigo": "IUP298-LOV-RT-212", "coleccion": "ARUBA NATURAL"}, {"codigo": "IUP298-OTT-111", "coleccion": "ARUBA NATURAL"}, {"codigo": "IUP298-OTT-121", "coleccion": "ARUBA NATURAL"}, {"codigo": "IUP298-OTT-131", "coleccion": "ARUBA NATURAL"}, {"codigo": "IUP298-OTT-151", "coleccion": "ARUBA NATURAL"}, {"codigo": "IUP298-OTT-152", "coleccion": "ARUBA NATURAL"}, {"codigo": "IUP298-OTT-161", "coleccion": "ARUBA NATURAL"}, {"codigo": "IUP298-OTT-210", "coleccion": "ARUBA NATURAL"}, {"codigo": "IUP298-OTT-212", "coleccion": "ARUBA NATURAL"}, {"codigo": "IUP298-SOF-111", "coleccion": "ARUBA NATURAL"}, {"codigo": "IUP298-SOF-111-A", "coleccion": "ARUBA NATURAL"}, {"codigo": "IUP298-SOF-121", "coleccion": "ARUBA NATURAL"}, {"codigo": "IUP298-SOF-131", "coleccion": "ARUBA NATURAL"}, {"codigo": "IUP298-SOF-131-A", "coleccion": "ARUBA NATURAL"}, {"codigo": "IUP298-SOF-151", "coleccion": "ARUBA NATURAL"}, {"codigo": "IUP298-SOF-151-A", "coleccion": "ARUBA NATURAL"}, {"codigo": "IUP298-SOF-152", "coleccion": "ARUBA NATURAL"}, {"codigo": "IUP298-SOF-152-A", "coleccion": "ARUBA NATURAL"}, {"codigo": "IUP298-SOF-161", "coleccion": "ARUBA NATURAL"}, {"codigo": "IUP298-SOF-161-A", "coleccion": "ARUBA NATURAL"}, {"codigo": "IUP298-SOF-202", "coleccion": "ARUBA NATURAL"}, {"codigo": "IUP298-SOF-210", "coleccion": "ARUBA NATURAL"}, {"codigo": "IUP298-SOF-212", "coleccion": "ARUBA NATURAL"}, {"codigo": "IUP298-SOF-231", "coleccion": "ARUBA NATURAL"}, {"codigo": "IUP325-ACH-101", "coleccion": "CAFÉ VERONA"}, {"codigo": "IUP325-ACH-111", "coleccion": "CAFÉ VERONA"}, {"codigo": "IUP325-ACH-182", "coleccion": "CAFÉ VERONA"}, {"codigo": "IUP325-ACH-184", "coleccion": "CAFÉ VERONA"}, {"codigo": "IUP325-ACH-216", "coleccion": "CAFÉ VERONA"}, {"codigo": "IUP325-ACH-302", "coleccion": "CAFÉ VERONA"}, {"codigo": "IUP325-LOV-101", "coleccion": "CAFÉ VERONA"}, {"codigo": "IUP325-LOV-111", "coleccion": "CAFÉ VERONA"}, {"codigo": "IUP325-LOV-182", "coleccion": "CAFÉ VERONA"}, {"codigo": "IUP325-LOV-184", "coleccion": "CAFÉ VERONA"}, {"codigo": "IUP325-LOV-216", "coleccion": "CAFÉ VERONA"}, {"codigo": "IUP325-LOV-302", "coleccion": "CAFÉ VERONA"}, {"codigo": "IUP325-SOF-101", "coleccion": "CAFÉ VERONA"}, {"codigo": "IUP325-SOF-111", "coleccion": "CAFÉ VERONA"}, {"codigo": "IUP325-SOF-182", "coleccion": "CAFÉ VERONA"}, {"codigo": "IUP325-SOF-184", "coleccion": "CAFÉ VERONA"}, {"codigo": "IUP325-SOF-216", "coleccion": "CAFÉ VERONA"}, {"codigo": "IUP325-SOF-302", "coleccion": "CAFÉ VERONA"}, {"codigo": "IUP331-ACH-101", "coleccion": "NA"}, {"codigo": "IUP331-ACH-111", "coleccion": "NA"}, {"codigo": "IUP331-ACH-121", "coleccion": "NA"}, {"codigo": "IUP331-ACH-131", "coleccion": "NA"}, {"codigo": "IUP331-ACH-151", "coleccion": "NA"}, {"codigo": "IUP331-ACH-161", "coleccion": "NA"}, {"codigo": "IUP331-ACH-202", "coleccion": "NA"}, {"codigo": "IUP331-ACH-210", "coleccion": "NA"}, {"codigo": "IUP331-ACH-212", "coleccion": "NA"}, {"codigo": "IUP331-ACH-221", "coleccion": "NA"}, {"codigo": "IUP331-OTT-101", "coleccion": "NA"}, {"codigo": "IUP331-OTT-111", "coleccion": "NA"}, {"codigo": "IUP331-OTT-121", "coleccion": "NA"}, {"codigo": "IUP331-OTT-131", "coleccion": "NA"}, {"codigo": "IUP331-OTT-161", "coleccion": "NA"}, {"codigo": "IUP331-OTT-202", "coleccion": "NA"}, {"codigo": "IUP331-OTT-210", "coleccion": "NA"}, {"codigo": "IUP331-OTT-212", "coleccion": "NA"}, {"codigo": "IUP331-OTT-221", "coleccion": "NA"}, {"codigo": "IUP342-ACH-182", "coleccion": "WALNUT"}, {"codigo": "IUP342-ACH-214", "coleccion": "WALNUT"}, {"codigo": "IUP342-ACH-216", "coleccion": "WALNUT"}, {"codigo": "IUP342-ACH-301", "coleccion": "WALNUT"}, {"codigo": "IUP342-LOV-182", "coleccion": "WALNUT"}, {"codigo": "IUP342-LOV-214", "coleccion": "WALNUT"}, {"codigo": "IUP342-LOV-216", "coleccion": "WALNUT"}, {"codigo": "IUP342-LOV-301", "coleccion": "WALNUT"}, {"codigo": "IUP342-SOF-152", "coleccion": "WALNUT"}, {"codigo": "IUP342-SOF-182", "coleccion": "WALNUT"}, {"codigo": "IUP342-SOF-216", "coleccion": "WALNUT"}, {"codigo": "IUP342-SOF-301", "coleccion": "WALNUT"}, {"codigo": "IUP401-ACH-101", "coleccion": "CAFÉ ARUBA"}, {"codigo": "IUP401-ACH-111", "coleccion": "CAFÉ ARUBA"}, {"codigo": "IUP401-ACH-121", "coleccion": "CAFÉ ARUBA"}, {"codigo": "IUP401-ACH-151", "coleccion": "CAFÉ ARUBA"}, {"codigo": "IUP401-ACH-152", "coleccion": "CAFÉ ARUBA"}, {"codigo": "IUP401-ACH-161", "coleccion": "CAFÉ ARUBA"}, {"codigo": "IUP401-ACH-202", "coleccion": "CAFÉ ARUBA"}, {"codigo": "IUP401-ACH-210", "coleccion": "CAFÉ ARUBA"}, {"codigo": "IUP401-ACH-212", "coleccion": "CAFÉ ARUBA"}, {"codigo": "IUP422-ACH-212", "coleccion": "BALAM"}, {"codigo": "IUP422-ACH-231", "coleccion": "BALAM"}, {"codigo": "IUP422-BST24-101", "coleccion": "BALAM"}, {"codigo": "IUP422-BST24-161", "coleccion": "BALAM"}, {"codigo": "IUP422-BST24-216", "coleccion": "BALAM"}, {"codigo": "IUP422-BST24-231", "coleccion": "BALAM"}, {"codigo": "IUP422-BST24-232", "coleccion": "BALAM"}, {"codigo": "IUP422-BST30-161", "coleccion": "BALAM"}, {"codigo": "IUP422-BST30-231", "coleccion": "BALAM"}, {"codigo": "IUP422-BST30-232", "coleccion": "BALAM"}, {"codigo": "IUP422-LOV-212", "coleccion": "BALAM"}, {"codigo": "IUP422-LOV-231", "coleccion": "BALAM"}, {"codigo": "IUP422-OTT-212", "coleccion": "BALAM"}, {"codigo": "IUP422-OTT-231", "coleccion": "BALAM"}, {"codigo": "IUP422-SOF-212", "coleccion": "BALAM"}, {"codigo": "IUP422-SOF-231", "coleccion": "BALAM"}, {"codigo": "IUP432-BST24-231", "coleccion": "WHITE BALAM"}, {"codigo": "IUP432-BST24-232", "coleccion": "BALAM"}, {"codigo": "IUP432-BST30-231", "coleccion": "WHITE BALAM"}, {"codigo": "IUP432-BST30-232", "coleccion": "WHITE BALAM"}, {"codigo": "IUP442-ACH-216", "coleccion": "BLACK BALAM"}, {"codigo": "IUP442-BST24-161", "coleccion": "BLACK BALAM"}, {"codigo": "IUP442-BST24-216", "coleccion": "BLACK BALAM"}, {"codigo": "IUP442-BST30-161", "coleccion": "BLACK BALAM"}, {"codigo": "IUP442-BST30-216", "coleccion": "BLACK BALAM"}, {"codigo": "IUP485-ACH-202", "coleccion": "RARAMURI"}, {"codigo": "IUP485-ACH-242", "coleccion": "RARAMURI"}, {"codigo": "IUP485-LOV-202", "coleccion": "RARAMURI"}, {"codigo": "IUP485-LOV-242", "coleccion": "RARAMURI"}, {"codigo": "IUP485-SOF-202", "coleccion": "RARAMURI"}, {"codigo": "IUP485-SOF-242", "coleccion": "RARAMURI"}, {"codigo": "IUP515-ACH-101", "coleccion": "NA"}, {"codigo": "IUP515-ACH-111", "coleccion": "NA"}, {"codigo": "IUP515-ACH-215", "coleccion": "NA"}, {"codigo": "IUP531-ACH-101", "coleccion": "PAROTA III"}, {"codigo": "IUP531-ACH-111", "coleccion": "PAROTA III"}, {"codigo": "IUP531-ACH-131", "coleccion": "PAROTA III"}, {"codigo": "IUP531-ACH-184", "coleccion": "PAROTA III"}, {"codigo": "IUP531-ACH-216", "coleccion": "PAROTA III"}, {"codigo": "IUP531-LOV-101", "coleccion": "PAROTA III"}, {"codigo": "IUP531-LOV-111", "coleccion": "PAROTA III"}, {"codigo": "IUP531-LOV-131", "coleccion": "PAROTA III"}, {"codigo": "IUP531-LOV-184", "coleccion": "PAROTA III"}, {"codigo": "IUP531-LOV-216", "coleccion": "PAROTA III"}, {"codigo": "IUP531-SOF-101", "coleccion": "PAROTA III"}, {"codigo": "IUP531-SOF-111", "coleccion": "PAROTA III"}, {"codigo": "IUP531-SOF-131", "coleccion": "PAROTA III"}, {"codigo": "IUP531-SOF-184", "coleccion": "PAROTA III"}, {"codigo": "IUP531-SOF-216", "coleccion": "PAROTA III"}, {"codigo": "IUP541-ACH-111", "coleccion": "OLIVO"}, {"codigo": "IUP541-ACH-152", "coleccion": "OLIVO"}, {"codigo": "IUP541-ACH-161", "coleccion": "OLIVO"}, {"codigo": "IUP541-ACH-202", "coleccion": "OLIVO"}, {"codigo": "IUP541-ACH-210", "coleccion": "OLIVO"}, {"codigo": "IUP541-ACH-212", "coleccion": "OLIVO"}, {"codigo": "IUP541-LOV-111", "coleccion": "OLIVO"}, {"codigo": "IUP541-LOV-152", "coleccion": "OLIVO"}, {"codigo": "IUP541-LOV-161", "coleccion": "OLIVO"}, {"codigo": "IUP541-LOV-202", "coleccion": "OLIVO"}, {"codigo": "IUP541-LOV-210", "coleccion": "OLIVO"}, {"codigo": "IUP541-LOV-212", "coleccion": "OLIVO"}, {"codigo": "IUP541-SOF-111", "coleccion": "OLIVO"}, {"codigo": "IUP541-SOF-152", "coleccion": "OLIVO"}, {"codigo": "IUP541-SOF-161", "coleccion": "OLIVO"}, {"codigo": "IUP541-SOF-202", "coleccion": "OLIVO"}, {"codigo": "IUP541-SOF-210", "coleccion": "OLIVO"}, {"codigo": "IUP541-SOF-212", "coleccion": "OLIVO"}, {"codigo": "IUP551-ACH-101", "coleccion": "CAFÉ ARUBA"}, {"codigo": "IUP551-ACH-111", "coleccion": "CAFÉ ARUBA"}, {"codigo": "IUP551-ACH-121", "coleccion": "CAFÉ ARUBA"}, {"codigo": "IUP551-ACH-151", "coleccion": "CAFÉ ARUBA"}, {"codigo": "IUP551-ACH-161", "coleccion": "CAFÉ ARUBA"}, {"codigo": "IUP551-ACH-210", "coleccion": "CAFÉ ARUBA"}, {"codigo": "IUP551-ACH-212", "coleccion": "CAFÉ ARUBA"}, {"codigo": "IUP551-LOV-101", "coleccion": "CAFÉ ARUBA"}, {"codigo": "IUP551-LOV-111", "coleccion": "CAFÉ ARUBA"}, {"codigo": "IUP551-LOV-121", "coleccion": "CAFÉ ARUBA"}, {"codigo": "IUP551-LOV-151", "coleccion": "CAFÉ ARUBA"}, {"codigo": "IUP551-LOV-161", "coleccion": "CAFÉ ARUBA"}, {"codigo": "IUP551-LOV-210", "coleccion": "CAFÉ ARUBA"}, {"codigo": "IUP551-LOV-212", "coleccion": "CAFÉ ARUBA"}, {"codigo": "IUP551-SOF-101", "coleccion": "CAFÉ ARUBA"}, {"codigo": "IUP551-SOF-111", "coleccion": "CAFÉ ARUBA"}, {"codigo": "IUP551-SOF-121", "coleccion": "CAFÉ ARUBA"}, {"codigo": "IUP551-SOF-151", "coleccion": "CAFÉ ARUBA"}, {"codigo": "IUP551-SOF-161", "coleccion": "CAFÉ ARUBA"}, {"codigo": "IUP551-SOF-210", "coleccion": "CAFÉ ARUBA"}, {"codigo": "IUP551-SOF-212", "coleccion": "CAFÉ ARUBA"}, {"codigo": "IUP572-BST24-231", "coleccion": "XELHA"}, {"codigo": "IUP572-BST30-231", "coleccion": "XELHA"}, {"codigo": "IUP574-ACH-183", "coleccion": "XELHA"}, {"codigo": "IUP574-ACH-232", "coleccion": "XELHA"}, {"codigo": "IUP574-LOV-183", "coleccion": "XELHA"}, {"codigo": "IUP574-LOV-232", "coleccion": "XELHA"}, {"codigo": "IUP574-SOF-183", "coleccion": "XELHA"}, {"codigo": "IUP574-SOF-232", "coleccion": "XELHA"}, {"codigo": "IUP595-ACH-239", "coleccion": "ZAPHIRO"}, {"codigo": "IUP595-LOV-239", "coleccion": "ZAPHIRO"}, {"codigo": "IUP595-SOF-239", "coleccion": "ZAPHIRO"}, {"codigo": "IUP611-ACH-101", "coleccion": "NA"}, {"codigo": "IUP611-ACH-111", "coleccion": "NA"}, {"codigo": "IUP611-ACH-121", "coleccion": "NA"}, {"codigo": "IUP611-ACH-161", "coleccion": "NA"}, {"codigo": "IUP611-ACH-202", "coleccion": "NA"}, {"codigo": "IUP611-ACH-210", "coleccion": "NA"}, {"codigo": "IUP611-ACH-212", "coleccion": "NA"}, {"codigo": "IUP611-ACH-215", "coleccion": "NA"}, {"codigo": "IUP611-ACH-216", "coleccion": "NA"}, {"codigo": "IUP611-ACH-221", "coleccion": "NA"}, {"codigo": "IUP611-ACH-232", "coleccion": "NA"}, {"codigo": "IUP612-ACH-210", "coleccion": "NA"}, {"codigo": "IUP644-ACH-111", "coleccion": "LOFT"}, {"codigo": "IUP644-ACH-121", "coleccion": "LOFT"}, {"codigo": "IUP644-ACH-151", "coleccion": "LOFT"}, {"codigo": "IUP644-ACH-152", "coleccion": "LOFT"}, {"codigo": "IUP644-ACH-161", "coleccion": "LOFT"}, {"codigo": "IUP644-ACH-201", "coleccion": "LOFT"}, {"codigo": "IUP644-ACH-202", "coleccion": "LOFT"}, {"codigo": "IUP644-ACH-210", "coleccion": "LOFT"}, {"codigo": "IUP644-ACH-212", "coleccion": "LOFT"}, {"codigo": "IUP644-ACH-214", "coleccion": "LOFT"}, {"codigo": "IUP644-ACH-216", "coleccion": "LOFT"}, {"codigo": "IUP644-ACH-221", "coleccion": "LOFT"}, {"codigo": "IUP644-LOV-111", "coleccion": "LOFT"}, {"codigo": "IUP644-LOV-121", "coleccion": "LOFT"}, {"codigo": "IUP644-LOV-151", "coleccion": "LOFT"}, {"codigo": "IUP644-LOV-152", "coleccion": "LOFT"}, {"codigo": "IUP644-LOV-161", "coleccion": "LOFT"}, {"codigo": "IUP644-LOV-202", "coleccion": "LOFT"}, {"codigo": "IUP644-LOV-210", "coleccion": "LOFT"}, {"codigo": "IUP644-LOV-212", "coleccion": "LOFT"}, {"codigo": "IUP644-LOV-216", "coleccion": "LOFT"}, {"codigo": "IUP644-LOV-221", "coleccion": "LOFT"}, {"codigo": "IUP644-SOF-111", "coleccion": "LOFT"}, {"codigo": "IUP644-SOF-121", "coleccion": "LOFT"}, {"codigo": "IUP644-SOF-131", "coleccion": "LOFT"}, {"codigo": "IUP644-SOF-151", "coleccion": "LOFT"}, {"codigo": "IUP644-SOF-152", "coleccion": "LOFT"}, {"codigo": "IUP644-SOF-161", "coleccion": "LOFT"}, {"codigo": "IUP644-SOF-201", "coleccion": "LOFT"}, {"codigo": "IUP644-SOF-202", "coleccion": "LOFT"}, {"codigo": "IUP644-SOF-210", "coleccion": "LOFT"}, {"codigo": "IUP644-SOF-211", "coleccion": "LOFT"}, {"codigo": "IUP644-SOF-212", "coleccion": "LOFT"}, {"codigo": "IUP644-SOF-214", "coleccion": "LOFT"}, {"codigo": "IUP644-SOF-216", "coleccion": "LOFT"}, {"codigo": "IUP644-SOF-221", "coleccion": "LOFT"}, {"codigo": "IUP654-BST24-101", "coleccion": "PRINCESS"}, {"codigo": "IUP654-BST24-210", "coleccion": "PRINCESS"}, {"codigo": "IUP654-BST30-101", "coleccion": "PRINCESS"}, {"codigo": "IUP662-ACH-161", "coleccion": "Mezquite"}, {"codigo": "IUP662-ACH-216", "coleccion": "Mezquite"}, {"codigo": "IUP662-ACH-232", "coleccion": "Mezquite"}, {"codigo": "IUP662-BST24-232", "coleccion": "Mezquite"}, {"codigo": "IUP662-BST30-232", "coleccion": "Mezquite"}, {"codigo": "IUP662-LOV-121", "coleccion": "Mezquite"}, {"codigo": "IUP662-LOV-161", "coleccion": "Mezquite"}, {"codigo": "IUP662-LOV-214", "coleccion": "Mezquite"}, {"codigo": "IUP662-LOV-232", "coleccion": "Mezquite"}, {"codigo": "IUP662-SOF-121", "coleccion": "Mezquite"}, {"codigo": "IUP662-SOF-161", "coleccion": "Mezquite"}, {"codigo": "IUP662-SOF-216", "coleccion": "Mezquite"}, {"codigo": "IUP662-SOF-232", "coleccion": "Mezquite"}, {"codigo": "IUP662-STL24-131", "coleccion": "NA"}, {"codigo": "IUP662-STL24-231", "coleccion": "NA"}, {"codigo": "IUP662-STL24-232", "coleccion": "NA"}, {"codigo": "IUP662-STL30-131", "coleccion": "NA"}, {"codigo": "IUP673-ACH-101", "coleccion": "BALAM"}, {"codigo": "IUP673-ACH-111", "coleccion": "BALAM"}, {"codigo": "IUP673-ACH-131", "coleccion": "BALAM"}, {"codigo": "IUP673-ACH-184", "coleccion": "BALAM"}, {"codigo": "IUP673-ACH-216", "coleccion": "BALAM"}, {"codigo": "IUP673-ACH-304", "coleccion": "BALAM"}, {"codigo": "IUP673-LOV-101", "coleccion": "BALAM"}, {"codigo": "IUP673-LOV-111", "coleccion": "BALAM"}, {"codigo": "IUP673-LOV-131", "coleccion": "BALAM"}, {"codigo": "IUP673-LOV-184", "coleccion": "BALAM"}, {"codigo": "IUP673-LOV-216", "coleccion": "BALAM"}, {"codigo": "IUP673-LOV-304", "coleccion": "BALAM"}, {"codigo": "IUP673-SOF-101", "coleccion": "BALAM"}, {"codigo": "IUP673-SOF-111", "coleccion": "BALAM"}, {"codigo": "IUP673-SOF-131", "coleccion": "BALAM"}, {"codigo": "IUP673-SOF-184", "coleccion": "BALAM"}, {"codigo": "IUP673-SOF-216", "coleccion": "BALAM"}, {"codigo": "IUP673-SOF-304", "coleccion": "BALAM"}, {"codigo": "IUP700-BST24-111", "coleccion": "CAFÉ ARUBA"}, {"codigo": "IUP700-BST24-121", "coleccion": "CAFÉ ARUBA"}, {"codigo": "IUP700-BST24-161", "coleccion": "CAFÉ ARUBA"}, {"codigo": "IUP700-BST24-210", "coleccion": "CAFÉ ARUBA"}, {"codigo": "IUP700-BST24-212", "coleccion": "CAFÉ ARUBA"}, {"codigo": "IUP700-BST30-111", "coleccion": "CAFÉ ARUBA"}, {"codigo": "IUP700-BST30-121", "coleccion": "CAFÉ ARUBA"}, {"codigo": "IUP700-BST30-161", "coleccion": "CAFÉ ARUBA"}, {"codigo": "IUP700-BST30-210", "coleccion": "CAFÉ ARUBA"}, {"codigo": "IUP700-BST30-212", "coleccion": "CAFÉ ARUBA"}, {"codigo": "IUP701-BST24-131", "coleccion": "NA"}, {"codigo": "IUP701-BST24-161", "coleccion": "NA"}, {"codigo": "IUP701-BST24-211", "coleccion": "NA"}, {"codigo": "IUP701-BST24-216", "coleccion": "NA"}, {"codigo": "IUP701-BST30-131", "coleccion": "NA"}, {"codigo": "IUP701-BST30-161", "coleccion": "NA"}, {"codigo": "IUP701-BST30-216", "coleccion": "NA"}, {"codigo": "IUP703-BST24-216", "coleccion": "NA"}, {"codigo": "IUP703-BST30-216", "coleccion": "NA"}, {"codigo": "IUP722-ACH-121", "coleccion": "CAFÉ ARUBA"}, {"codigo": "IUP722-ACH-151", "coleccion": "CAFÉ ARUBA"}, {"codigo": "IUP722-ACH-152", "coleccion": "CAFÉ ARUBA"}, {"codigo": "IUP722-ACH-161", "coleccion": "CAFÉ ARUBA"}, {"codigo": "IUP722-ACH-202", "coleccion": "CAFÉ ARUBA"}, {"codigo": "IUP722-ACH-210", "coleccion": "CAFÉ ARUBA"}, {"codigo": "IUP722-ACH-212", "coleccion": "CAFÉ ARUBA"}, {"codigo": "IUP722-ACH-221", "coleccion": "CAFÉ ARUBA"}, {"codigo": "IUP722-ALC-121", "coleccion": "CAFÉ ARUBA"}, {"codigo": "IUP722-ALC-151", "coleccion": "CAFÉ ARUBA"}, {"codigo": "IUP722-ALC-152", "coleccion": "CAFÉ ARUBA"}, {"codigo": "IUP722-ALC-161", "coleccion": "CAFÉ ARUBA"}, {"codigo": "IUP722-ALC-202", "coleccion": "CAFÉ ARUBA"}, {"codigo": "IUP722-ALC-210", "coleccion": "CAFÉ ARUBA"}, {"codigo": "IUP722-ALC-212", "coleccion": "CAFÉ ARUBA"}, {"codigo": "IUP722-ALC-221", "coleccion": "CAFÉ ARUBA"}, {"codigo": "IUP722-LOV-121", "coleccion": "CAFÉ ARUBA"}, {"codigo": "IUP722-LOV-151", "coleccion": "CAFÉ ARUBA"}, {"codigo": "IUP722-LOV-152", "coleccion": "CAFÉ ARUBA"}, {"codigo": "IUP722-LOV-161", "coleccion": "CAFÉ ARUBA"}, {"codigo": "IUP722-LOV-202", "coleccion": "CAFÉ ARUBA"}, {"codigo": "IUP722-LOV-210", "coleccion": "CAFÉ ARUBA"}, {"codigo": "IUP722-LOV-212", "coleccion": "CAFÉ ARUBA"}, {"codigo": "IUP722-LOV-221", "coleccion": "CAFÉ ARUBA"}, {"codigo": "IUP722-LOV-LF-121", "coleccion": "CAFÉ ARUBA"}, {"codigo": "IUP722-LOV-LF-151", "coleccion": "CAFÉ ARUBA"}, {"codigo": "IUP722-LOV-LF-152", "coleccion": "CAFÉ ARUBA"}, {"codigo": "IUP722-LOV-LF-161", "coleccion": "CAFÉ ARUBA"}, {"codigo": "IUP722-LOV-LF-202", "coleccion": "CAFÉ ARUBA"}, {"codigo": "IUP722-LOV-LF-210", "coleccion": "CAFÉ ARUBA"}, {"codigo": "IUP722-LOV-LF-212", "coleccion": "CAFÉ ARUBA"}, {"codigo": "IUP722-LOV-LF-221", "coleccion": "CAFÉ ARUBA"}, {"codigo": "IUP722-LOV-RT-121", "coleccion": "CAFÉ ARUBA"}, {"codigo": "IUP722-LOV-RT-151", "coleccion": "CAFÉ ARUBA"}, {"codigo": "IUP722-LOV-RT-152", "coleccion": "CAFÉ ARUBA"}, {"codigo": "IUP722-LOV-RT-161", "coleccion": "CAFÉ ARUBA"}, {"codigo": "IUP722-LOV-RT-202", "coleccion": "CAFÉ ARUBA"}, {"codigo": "IUP722-LOV-RT-210", "coleccion": "CAFÉ ARUBA"}, {"codigo": "IUP722-LOV-RT-212", "coleccion": "CAFÉ ARUBA"}, {"codigo": "IUP722-LOV-RT-221", "coleccion": "CAFÉ ARUBA"}, {"codigo": "IUP722-OTT-121", "coleccion": "CAFÉ ARUBA"}, {"codigo": "IUP722-OTT-151", "coleccion": "CAFÉ ARUBA"}, {"codigo": "IUP722-OTT-152", "coleccion": "CAFÉ ARUBA"}, {"codigo": "IUP722-OTT-161", "coleccion": "CAFÉ ARUBA"}, {"codigo": "IUP722-OTT-202", "coleccion": "CAFÉ ARUBA"}, {"codigo": "IUP722-OTT-210", "coleccion": "CAFÉ ARUBA"}, {"codigo": "IUP722-OTT-212", "coleccion": "CAFÉ ARUBA"}, {"codigo": "IUP722-OTT-221", "coleccion": "CAFÉ ARUBA"}, {"codigo": "IUP722-SOF-121", "coleccion": "CAFÉ ARUBA"}, {"codigo": "IUP722-SOF-151", "coleccion": "CAFÉ ARUBA"}, {"codigo": "IUP722-SOF-152", "coleccion": "CAFÉ ARUBA"}, {"codigo": "IUP722-SOF-161", "coleccion": "CAFÉ ARUBA"}, {"codigo": "IUP722-SOF-202", "coleccion": "CAFÉ ARUBA"}, {"codigo": "IUP722-SOF-210", "coleccion": "CAFÉ ARUBA"}, {"codigo": "IUP722-SOF-212", "coleccion": "CAFÉ ARUBA"}, {"codigo": "IUP722-SOF-221", "coleccion": "CAFÉ ARUBA"}, {"codigo": "IUP722-WDG-SQ-121", "coleccion": "CAFÉ ARUBA"}, {"codigo": "IUP722-WDG-SQ-151", "coleccion": "CAFÉ ARUBA"}, {"codigo": "IUP722-WDG-SQ-152", "coleccion": "CAFÉ ARUBA"}, {"codigo": "IUP722-WDG-SQ-161", "coleccion": "CAFÉ ARUBA"}, {"codigo": "IUP722-WDG-SQ-202", "coleccion": "CAFÉ ARUBA"}, {"codigo": "IUP722-WDG-SQ-210", "coleccion": "CAFÉ ARUBA"}, {"codigo": "IUP722-WDG-SQ-212", "coleccion": "CAFÉ ARUBA"}, {"codigo": "IUP722-WDG-SQ-221", "coleccion": "CAFÉ ARUBA"}, {"codigo": "IUP738-ACH-101", "coleccion": "OLIMPIA"}, {"codigo": "IUP738-ACH-111", "coleccion": "OLIMPIA"}, {"codigo": "IUP738-ACH-152", "coleccion": "OLIMPIA"}, {"codigo": "IUP738-ACH-161", "coleccion": "OLIMPIA"}, {"codigo": "IUP738-ACH-210", "coleccion": "OLIMPIA"}, {"codigo": "IUP738-ACH-212", "coleccion": "OLIMPIA"}, {"codigo": "IUP738-LOV-101", "coleccion": "OLIMPIA"}, {"codigo": "IUP738-LOV-111", "coleccion": "OLIMPIA"}, {"codigo": "IUP738-LOV-152", "coleccion": "OLIMPIA"}, {"codigo": "IUP738-LOV-161", "coleccion": "OLIMPIA"}, {"codigo": "IUP738-LOV-210", "coleccion": "OLIMPIA"}, {"codigo": "IUP738-LOV-212", "coleccion": "OLIMPIA"}, {"codigo": "IUP738-SOF-101", "coleccion": "OLIMPIA"}, {"codigo": "IUP738-SOF-111", "coleccion": "OLIMPIA"}, {"codigo": "IUP738-SOF-152", "coleccion": "OLIMPIA"}, {"codigo": "IUP738-SOF-161", "coleccion": "OLIMPIA"}, {"codigo": "IUP738-SOF-210", "coleccion": "OLIMPIA"}, {"codigo": "IUP738-SOF-212", "coleccion": "OLIMPIA"}, {"codigo": "IUP800-BST24-111", "coleccion": "NA"}, {"codigo": "IUP800-BST24-121", "coleccion": "NA"}, {"codigo": "IUP800-BST24-161", "coleccion": "NA"}, {"codigo": "IUP800-BST24-202", "coleccion": "NA"}, {"codigo": "IUP800-BST24-210", "coleccion": "NA"}, {"codigo": "IUP800-BST24-212", "coleccion": "NA"}, {"codigo": "IUP800-BST24-232", "coleccion": "NA"}, {"codigo": "IUP800-BST30-111", "coleccion": "NA"}, {"codigo": "IUP800-BST30-121", "coleccion": "NA"}, {"codigo": "IUP800-BST30-161", "coleccion": "NA"}, {"codigo": "IUP800-BST30-202", "coleccion": "NA"}, {"codigo": "IUP800-BST30-210", "coleccion": "NA"}, {"codigo": "IUP800-BST30-212", "coleccion": "NA"}, {"codigo": "IUP800-BST30-232", "coleccion": "NA"}, {"codigo": "IUP800-CHU-161", "coleccion": "NA"}, {"codigo": "IUP800-CHU-202", "coleccion": "NA"}, {"codigo": "IUP800-CHU-210", "coleccion": "NA"}, {"codigo": "IUP800-CHU-212", "coleccion": "NA"}, {"codigo": "IUP800-CHU-231", "coleccion": "NA"}, {"codigo": "IUP800-CHU-232", "coleccion": "NA"}, {"codigo": "IUP801-BST24-111", "coleccion": "NA"}, {"codigo": "IUP801-BST24-202", "coleccion": "NA"}, {"codigo": "IUP801-BST24-210", "coleccion": "NA"}, {"codigo": "IUP801-BST24-211", "coleccion": "NA"}, {"codigo": "IUP801-BST24-212", "coleccion": "NA"}, {"codigo": "IUP801-BST30-111", "coleccion": "NA"}, {"codigo": "IUP801-BST30-202", "coleccion": "NA"}, {"codigo": "IUP801-BST30-210", "coleccion": "NA"}, {"codigo": "IUP801-BST30-211", "coleccion": "NA"}, {"codigo": "IUP801-BST30-212", "coleccion": "NA"}, {"codigo": "IUP802-STL24-161", "coleccion": "NA"}, {"codigo": "IUP802-STL24-202", "coleccion": "NA"}, {"codigo": "IUP802-STL24-210", "coleccion": "NA"}, {"codigo": "IUP802-STL24-211", "coleccion": "NA"}, {"codigo": "IUP802-STL24-212", "coleccion": "NA"}, {"codigo": "IUP802-STL24-232", "coleccion": "NA"}, {"codigo": "IUP802-STL30-111", "coleccion": "NA"}, {"codigo": "IUP802-STL30-161", "coleccion": "NA"}, {"codigo": "IUP802-STL30-202", "coleccion": "NA"}, {"codigo": "IUP802-STL30-210", "coleccion": "NA"}, {"codigo": "IUP802-STL30-211", "coleccion": "NA"}, {"codigo": "IUP802-STL30-212", "coleccion": "NA"}, {"codigo": "IUP803-BST24-111", "coleccion": "NA"}, {"codigo": "IUP803-BST24-161", "coleccion": "NA"}, {"codigo": "IUP803-BST24-202", "coleccion": "NA"}, {"codigo": "IUP803-BST24-210", "coleccion": "NA"}, {"codigo": "IUP803-BST24-212", "coleccion": "NA"}, {"codigo": "IUP803-BST30-111", "coleccion": "NA"}, {"codigo": "IUP803-BST30-161", "coleccion": "NA"}, {"codigo": "IUP803-BST30-202", "coleccion": "NA"}, {"codigo": "IUP803-BST30-210", "coleccion": "NA"}, {"codigo": "IUP803-BST30-212", "coleccion": "NA"}, {"codigo": "IUP805-BST24-216", "coleccion": "PAROTA III"}, {"codigo": "IUP805-BST30-216", "coleccion": "PAROTA III"}, {"codigo": "IUP806-BST24-216", "coleccion": "NA"}, {"codigo": "IUP806-BST30-216", "coleccion": "NA"}, {"codigo": "IUP807-BST24-101", "coleccion": "NA"}, {"codigo": "IUP807-BST24-131", "coleccion": "NA"}, {"codigo": "IUP807-BST24-161", "coleccion": "NA"}, {"codigo": "IUP807-BST24-210", "coleccion": "NA"}, {"codigo": "IUP807-BST30-101", "coleccion": "NA"}, {"codigo": "IUP807-BST30-131", "coleccion": "NA"}, {"codigo": "IUP807-BST30-210", "coleccion": "NA"}, {"codigo": "IUP815-STL24-216", "coleccion": "NA"}, {"codigo": "IUP816-BST24-111", "coleccion": "NA"}, {"codigo": "IUP816-BST30-111", "coleccion": "NA"}, {"codigo": "IUP817-BST2430-216", "coleccion": "NA"}, {"codigo": "IUP817-BST2430-239", "coleccion": "NA"}, {"codigo": "IUP823-BST30-202", "coleccion": "NA"}, {"codigo": "IUP854-ACH-111", "coleccion": "NA"}, {"codigo": "IUP854-ACH-121", "coleccion": "NA"}, {"codigo": "IUP854-ACH-152", "coleccion": "NA"}, {"codigo": "IUP854-ACH-161", "coleccion": "NA"}, {"codigo": "IUP854-ACH-202", "coleccion": "NA"}, {"codigo": "IUP854-ACH-210", "coleccion": "NA"}, {"codigo": "IUP854-ACH-212", "coleccion": "NA"}, {"codigo": "IUP854-ACH-216", "coleccion": "NA"}, {"codigo": "IUP854-ACH-221", "coleccion": "NA"}, {"codigo": "IUP854-ACH-232", "coleccion": "NA"}, {"codigo": "IUP854-ACH-261", "coleccion": "NA"}, {"codigo": "IUP868-ACH-151", "coleccion": "CAFÉ SUGAR"}, {"codigo": "IUP868-ACH-152", "coleccion": "CAFÉ SUGAR"}, {"codigo": "IUP868-ACH-161", "coleccion": "CAFÉ SUGAR"}, {"codigo": "IUP868-ACH-210", "coleccion": "CAFÉ SUGAR"}, {"codigo": "IUP868-ACH-212", "coleccion": "CAFÉ SUGAR"}, {"codigo": "IUP868-LOV-151", "coleccion": "CAFÉ SUGAR"}, {"codigo": "IUP868-LOV-152", "coleccion": "CAFÉ SUGAR"}, {"codigo": "IUP868-LOV-161", "coleccion": "CAFÉ SUGAR"}, {"codigo": "IUP868-LOV-210", "coleccion": "CAFÉ SUGAR"}, {"codigo": "IUP868-LOV-212", "coleccion": "CAFÉ SUGAR"}, {"codigo": "IUP868-SOF-151", "coleccion": "CAFÉ SUGAR"}, {"codigo": "IUP868-SOF-152", "coleccion": "CAFÉ SUGAR"}, {"codigo": "IUP868-SOF-161", "coleccion": "CAFÉ SUGAR"}, {"codigo": "IUP868-SOF-210", "coleccion": "CAFÉ SUGAR"}, {"codigo": "IUP868-SOF-212", "coleccion": "CAFÉ SUGAR"}, {"codigo": "IUP868-SOF-221", "coleccion": "CAFÉ SUGAR"}, {"codigo": "IUP882-ACH-111", "coleccion": "CAFÉ ARUBA"}, {"codigo": "IUP882-ACH-121", "coleccion": "CAFÉ ARUBA"}, {"codigo": "IUP882-ACH-151", "coleccion": "CAFÉ ARUBA"}, {"codigo": "IUP882-ACH-152", "coleccion": "CAFÉ ARUBA"}, {"codigo": "IUP882-ACH-161", "coleccion": "CAFÉ ARUBA"}, {"codigo": "IUP882-ACH-210", "coleccion": "CAFÉ ARUBA"}, {"codigo": "IUP882-ACH-212", "coleccion": "CAFÉ ARUBA"}, {"codigo": "IUP882-ACH-221", "coleccion": "CAFÉ ARUBA"}, {"codigo": "IUP882-LOV-121", "coleccion": "CAFÉ ARUBA"}, {"codigo": "IUP882-LOV-151", "coleccion": "CAFÉ ARUBA"}, {"codigo": "IUP882-LOV-152", "coleccion": "CAFÉ ARUBA"}, {"codigo": "IUP882-LOV-161", "coleccion": "CAFÉ ARUBA"}, {"codigo": "IUP882-LOV-210", "coleccion": "CAFÉ ARUBA"}, {"codigo": "IUP882-LOV-212", "coleccion": "CAFÉ ARUBA"}, {"codigo": "IUP882-LOV-221", "coleccion": "CAFÉ ARUBA"}, {"codigo": "IUP882-SOF-111", "coleccion": "CAFÉ ARUBA"}, {"codigo": "IUP882-SOF-121", "coleccion": "CAFÉ ARUBA"}, {"codigo": "IUP882-SOF-151", "coleccion": "CAFÉ ARUBA"}, {"codigo": "IUP882-SOF-152", "coleccion": "CAFÉ ARUBA"}, {"codigo": "IUP882-SOF-161", "coleccion": "CAFÉ ARUBA"}, {"codigo": "IUP882-SOF-210", "coleccion": "CAFÉ ARUBA"}, {"codigo": "IUP882-SOF-212", "coleccion": "CAFÉ ARUBA"}, {"codigo": "IUP882-SOF-221", "coleccion": "CAFÉ ARUBA"}, {"codigo": "IUP966-ACH-101", "coleccion": "CAFÉ SAHARA"}, {"codigo": "IUP966-ACH-111", "coleccion": "CAFÉ SAHARA"}, {"codigo": "IUP966-ACH-121", "coleccion": "CAFÉ SAHARA"}, {"codigo": "IUP966-ACH-131", "coleccion": "CAFÉ SAHARA"}, {"codigo": "IUP966-ACH-152", "coleccion": "CAFÉ SAHARA"}, {"codigo": "IUP966-ACH-161", "coleccion": "CAFÉ SAHARA"}, {"codigo": "IUP966-ACH-202", "coleccion": "CAFÉ SAHARA"}, {"codigo": "IUP966-ACH-210", "coleccion": "CAFÉ SAHARA"}, {"codigo": "IUP966-ACH-212", "coleccion": "CAFÉ SAHARA"}, {"codigo": "IUP966-ACH-214", "coleccion": "CAFÉ SAHARA"}, {"codigo": "IUP966-ACH-216", "coleccion": "CAFÉ SAHARA"}, {"codigo": "IUP966-LOV-101", "coleccion": "CAFÉ SAHARA"}, {"codigo": "IUP966-LOV-111", "coleccion": "CAFÉ SAHARA"}, {"codigo": "IUP966-LOV-121", "coleccion": "CAFÉ SAHARA"}, {"codigo": "IUP966-LOV-131", "coleccion": "CAFÉ SAHARA"}, {"codigo": "IUP966-LOV-152", "coleccion": "CAFÉ SAHARA"}, {"codigo": "IUP966-LOV-161", "coleccion": "CAFÉ SAHARA"}, {"codigo": "IUP966-LOV-202", "coleccion": "CAFÉ SAHARA"}, {"codigo": "IUP966-LOV-210", "coleccion": "CAFÉ SAHARA"}, {"codigo": "IUP966-LOV-212", "coleccion": "CAFÉ SAHARA"}, {"codigo": "IUP966-LOV-216", "coleccion": "CAFÉ SAHARA"}, {"codigo": "IUP966-SOF-101", "coleccion": "CAFÉ SAHARA"}, {"codigo": "IUP966-SOF-111", "coleccion": "CAFÉ SAHARA"}, {"codigo": "IUP966-SOF-121-A", "coleccion": "CAFÉ SAHARA"}, {"codigo": "IUP966-SOF-131", "coleccion": "CAFÉ SAHARA"}, {"codigo": "IUP966-SOF-152", "coleccion": "CAFÉ SAHARA"}, {"codigo": "IUP966-SOF-161", "coleccion": "CAFÉ SAHARA"}, {"codigo": "IUP966-SOF-161-A", "coleccion": "CAFÉ SAHARA"}, {"codigo": "IUP966-SOF-202", "coleccion": "CAFÉ SAHARA"}, {"codigo": "IUP966-SOF-210", "coleccion": "CAFÉ SAHARA"}, {"codigo": "IUP966-SOF-212", "coleccion": "CAFÉ SAHARA"}, {"codigo": "IUP966-SOF-214", "coleccion": "CAFÉ SAHARA"}, {"codigo": "IUP966-SOF-216", "coleccion": "CAFÉ SAHARA"}]